check50_checkstyle/__init__.py
check50_checkstyle/lib/checkstyle-8.39-all.jar
check50_checkstyle-0.4.dist-info/LICENSE
check50_checkstyle-0.4.dist-info/METADATA
check50_checkstyle-0.4.dist-info/WHEEL
check50_checkstyle-0.4.dist-info/top_level.txt
check50_checkstyle-0.4.dist-info/RECORD
