Metadata-Version: 2.1
Name: check50-checkstyle
Version: 0.4
Summary: A check50 extension that wraps around the static code analyser checkstye(.org)
Home-page: https://github.com/pazz/check50_checkstyle
Author: Patrick Totzke
Author-email: patricktotzke@gmail.com
License: UNKNOWN
Platform: UNKNOWN
Classifier: Programming Language :: Python :: 3
Classifier: License :: OSI Approved :: MIT License
Classifier: Operating System :: OS Independent
Requires-Python: >=3.6
Requires-Dist: check50
